bad_mason/__init__.py
bad_mason/__main__.py
bad_mason/covid19getter.py
bad_mason/datahelper.zip
bad_mason-1.0.1.dist-info/LICENSE
bad_mason-1.0.1.dist-info/METADATA
bad_mason-1.0.1.dist-info/WHEEL
bad_mason-1.0.1.dist-info/entry_points.txt
bad_mason-1.0.1.dist-info/top_level.txt
bad_mason-1.0.1.dist-info/RECORD
