Metadata-Version: 2.1
Name: bad-mason
Version: 1.0.1
Summary: fake get useful data but do something evil
Home-page: https://github.com/Mason-Lin/bad_mason
Author: Bad Mason
Author-email: pizza.0117@gmail.com
License: UNKNOWN
Platform: UNKNOWN
Classifier: Programming Language :: Python :: 3
Classifier: License :: OSI Approved :: MIT License
Classifier: Operating System :: OS Independent
Requires-Dist: requires
